strings/__init__.py
strings/compare.py
compare_strings_lib-0.0.2.dist-info/METADATA
compare_strings_lib-0.0.2.dist-info/WHEEL
compare_strings_lib-0.0.2.dist-info/top_level.txt
compare_strings_lib-0.0.2.dist-info/RECORD
