Metadata-Version: 2.1
Name: compare-strings-lib
Version: 0.0.2
Summary: module for comparing to strings
Home-page: https://github.com/qalfaki/py-lib/tree/master/cs_lib
Author: qalfaki
Author-email: qusai.alfaki@gmail.com
License: UNKNOWN
Platform: UNKNOWN
Classifier: Programming Language :: Python :: 3
Classifier: License :: OSI Approved :: MIT License
Classifier: Operating System :: OS Independent
Requires-Python: >=3.6
